etspi/__init__.py
etspi/cli.py
etspi/commands/__init__.py
etspi/commands/cmd_auth.py
etspi/commands/cmd_draft.py
etspi/commands/cmd_file-delete.py
etspi/commands/cmd_file-get.py
etspi/commands/cmd_file-upload.py
etspi/commands/cmd_image-delete.py
etspi/commands/cmd_image-get.py
etspi/commands/cmd_image-upload.py
etspi/commands/cmd_listing-delete.py
etspi/commands/cmd_listing-get-iv.py
etspi/commands/cmd_listing-get.py
etspi/commands/cmd_listing-update-iv.py
etspi/commands/cmd_listing-update.py
etspi/commands/cmd_prop-get.py
etspi/commands/cmd_prop-update.py
etspi/commands/cmd_shop-find.py
etspi/commands/cmd_shop-get.py
etspi/commands/cmd_user.py
etspi/commands/cmd_video-delete.py
etspi/commands/cmd_video-get.py
etspi/commands/cmd_video-upload.py
etspi/etsyv3/__init__.py
etspi/etsyv3/enums/__init__.py
etspi/etsyv3/enums/listing.py
etspi/etsyv3/enums/shipping_providers.py
etspi/etsyv3/etsy_api.py
etspi/etsyv3/LICENSE
etspi/etsyv3/models/__init__.py
etspi/etsyv3/models/file_request.py
etspi/etsyv3/models/listing_inventory.py
etspi/etsyv3/models/listing_property.py
etspi/etsyv3/models/listing_request.py
etspi/etsyv3/models/product.py
etspi/etsyv3/models/receipt_request.py
etspi/etsyv3/models/shop_request.py
etspi/etsyv3/README.md
etspi/etsyv3/util/__init__.py
etspi/etsyv3/util/auth/__init__.py
etspi/etsyv3/util/auth/auth_helper.py
etspi/etsyv3/util/todict.py
etspi-1.0.4.dist-info/entry_points.txt
etspi-1.0.4.dist-info/LICENSE
etspi-1.0.4.dist-info/METADATA
etspi-1.0.4.dist-info/WHEEL
etspi-1.0.4.dist-info/RECORD
