Metadata-Version: 2.1
Name: etspi
Version: 1.0.4
Summary: CLI App to manage Etsy shop and listings.
Home-page: https://github.com/sov2000/etspi-cli
License: MIT
Keywords: etsy,api,shop,manager
Author: sov2000
Author-email: sv28k64@gmail.com
Requires-Python: >=3.12,<4.0
Classifier: Environment :: Console
Classifier: Intended Audience :: End Users/Desktop
Classifier: Intended Audience :: Other Audience
Classifier: License :: OSI Approved :: GNU General Public License v3 (GPLv3)
Classifier: License :: OSI Approved :: MIT License
Classifier: Operating System :: Microsoft :: Windows
Classifier: Operating System :: OS Independent
Classifier: Operating System :: POSIX
Classifier: Programming Language :: Python
Classifier: Programming Language :: Python :: 3
Classifier: Programming Language :: Python :: 3.12
Classifier: Programming Language :: Python :: 3.13
Classifier: Programming Language :: Python :: 3.14
Classifier: Topic :: Office/Business
Requires-Dist: certifi (>=2024.12.14,<2025.0.0)
Requires-Dist: charset-normalizer (>=3.4.0,<4.0.0)
Requires-Dist: click (>=8.1.7,<9.0.0)
Requires-Dist: idna (>=3.10,<4.0)
Requires-Dist: jmespath (>=1.0.1,<2.0.0)
Requires-Dist: oauthlib (>=3.2.2,<4.0.0)
Requires-Dist: python-dotenv (>=1.0.1,<2.0.0)
Requires-Dist: requests (>=2.32.3,<3.0.0)
Requires-Dist: requests-oauthlib (>=2.0.0,<3.0.0)
Requires-Dist: rich (>=13.9.4,<14.0.0)
Requires-Dist: setuptools (>=75.6.0,<76.0.0)
Requires-Dist: urllib3 (>=2.2.3,<3.0.0)
Project-URL: Repository, https://github.com/sov2000/etspi-cli
